{"type": "Feature", "id": 12510984, "properties": {"woe:id": 12510984, "woe:parent_id": 830707, "woe:name": "Rodnyaeast Airport", "woe:placetype": 14, "woe:placetype_name": "Airport", "woe:lang": "ENG", "iso:country": "BY", "meta:provider": ["geoplanet:7.3.1", "geoplanet:7.3.2", "geoplanet:7.4.0", "geoplanet:7.4.1", "geoplanet:7.5.1", "geoplanet:7.5.2", "geoplanet:7.6.0", "geoplanet:7.8.1", "geoplanet:7.9.0", "geoplanet:7.10.0", "geoplanet:8.0.0", "woeplanet:8.0.0"], "meta:indexed": "2020-08-20T21:02:19.456522", "meta:updated": "2020-08-22T01:58:41.651029", "woe:hierarchy": {"continent": 24865675, "country": 23424765, "town": 0, "planet": 1, "county": 0, "suburb": 0, "state": 2344833, "region": 0, "localadmin": 0}, "woe:timezone_id": 28350907, "woe:hash": "u9wbkwq88wyd", "woe:centroid": [32.198898, 53.5159], "geom:latitude": 53.5159, "geom:longitude": 32.198898, "geom:hash": "u9wbkwq88wyd", "woe:latitude": 53.5159, "geom:centroid": [32.198898, 53.5159], "woe:longitude": 32.198898, "woe:repo": "woeplanet-airport-by"}, "geometry": {"coordinates": [32.198898, 53.5159], "type": "Point"}}