{"type": "Feature", "id": 12510960, "geometry": {"type": "Point", "coordinates": [25.2719, 53.930698]}, "properties": {"woe:id": 12510960, "woe:parent_id": 827330, "woe:name": "Lida North Airport", "woe:placetype": 14, "woe:placetype_name": "Airport", "woe:lang": "ENG", "iso:country": "BY", "meta:provider": ["geoplanet:7.3.1", "geoplanet:7.3.2", "geoplanet:7.4.0", "geoplanet:7.4.1", "geoplanet:7.5.1", "geoplanet:7.5.2", "geoplanet:7.6.0", "geoplanet:7.8.1", "geoplanet:7.9.0", "geoplanet:7.10.0", "geoplanet:8.0.0", "woeplanet:8.0.0"], "meta:indexed": "2020-08-20T21:02:19.436589", "meta:updated": "2020-10-14T11:07:19.362050", "woe:hierarchy": {"continent": 24865675, "country": 23424765, "town": 0, "planet": 1, "county": 0, "suburb": 0, "state": 2344832, "region": 0, "localadmin": 0}, "woe:timezone_id": 28350907, "woe:hash": "u99fz1f3jfy2", "woe:centroid": [25.2719, 53.930698], "geom:latitude": 53.930698, "geom:longitude": 25.2719, "geom:hash": "u99fz1f3jfy2", "woe:latitude": 53.930698, "geom:centroid": [25.2719, 53.930698], "woe:longitude": 25.2719, "woe:repo": "woeplanet-airport-by", "geom:area": 0.0, "woe:scale": 19}}