{"type": "Feature", "id": 12510965, "properties": {"woe:id": 12510965, "woe:parent_id": 834463, "woe:name": "Minsk Northeast Airport", "woe:placetype": 14, "woe:placetype_name": "Airport", "woe:lang": "ENG", "iso:country": "BY", "meta:provider": ["geoplanet:7.3.1", "geoplanet:7.3.2", "geoplanet:7.4.0", "geoplanet:7.4.1", "geoplanet:7.5.1", "geoplanet:7.5.2", "geoplanet:7.6.0", "geoplanet:7.8.1", "geoplanet:7.9.0", "geoplanet:7.10.0", "geoplanet:8.0.0", "woeplanet:8.0.0"], "meta:indexed": "2020-08-20T21:02:19.440678", "meta:updated": "2020-08-22T01:58:41.644542", "woe:hierarchy": {"continent": 24865675, "country": 23424765, "town": 0, "planet": 1, "county": 0, "suburb": 0, "state": 2344834, "region": 0, "localadmin": 0}, "woe:timezone_id": 28350907, "woe:hash": "u9eej0sunkk9", "woe:centroid": [27.648399, 53.9683], "geom:latitude": 53.9683, "geom:longitude": 27.648399, "geom:hash": "u9eej0sunkk9", "woe:latitude": 53.9683, "geom:centroid": [27.648399, 53.9683], "woe:longitude": 27.648399, "woe:repo": "woeplanet-airport-by"}, "geometry": {"coordinates": [27.648399, 53.9683], "type": "Point"}}