{"type": "Feature", "id": 12510943, "properties": {"woe:id": 12510943, "woe:parent_id": 831800, "woe:name": "Bobr East Airport", "woe:placetype": 14, "woe:placetype_name": "Airport", "woe:lang": "ENG", "iso:country": "BY", "meta:provider": ["geoplanet:7.3.1", "geoplanet:7.3.2", "geoplanet:7.4.0", "geoplanet:7.4.1", "geoplanet:7.5.1", "geoplanet:7.5.2", "geoplanet:7.6.0", "geoplanet:7.8.1", "geoplanet:7.9.0", "geoplanet:7.10.0", "geoplanet:8.0.0", "woeplanet:8.0.0"], "meta:indexed": "2020-08-20T21:02:19.422262", "meta:updated": "2020-08-22T01:58:41.636257", "woe:hierarchy": {"continent": 24865675, "country": 23424765, "town": 0, "planet": 1, "county": 0, "suburb": 0, "state": 2344835, "region": 0, "localadmin": 0}, "woe:timezone_id": 28350907, "woe:hash": "u9svksrjvep4", "woe:centroid": [29.3873, 54.384701], "geom:latitude": 54.384701, "geom:longitude": 29.3873, "geom:hash": "u9svksrjvep4", "woe:latitude": 54.384701, "geom:centroid": [29.3873, 54.384701], "woe:longitude": 29.3873, "woe:repo": "woeplanet-airport-by"}, "geometry": {"coordinates": [29.3873, 54.384701], "type": "Point"}}